imgurapi-1.1.9.1.dist-info/DESCRIPTION.rst
imgurapi-1.1.9.1.dist-info/METADATA
imgurapi-1.1.9.1.dist-info/RECORD
imgurapi-1.1.9.1.dist-info/WHEEL
imgurapi-1.1.9.1.dist-info/metadata.json
imgurapi-1.1.9.1.dist-info/top_level.txt
imgurpython/__init__.py
imgurpython/client.py
imgurpython/helpers/__init__.py
imgurpython/helpers/error.py
imgurpython/helpers/format.py
imgurpython/imgur/__init__.py
imgurpython/imgur/models/__init__.py
imgurpython/imgur/models/account.py
imgurpython/imgur/models/account_settings.py
imgurpython/imgur/models/album.py
imgurpython/imgur/models/comment.py
imgurpython/imgur/models/conversation.py
imgurpython/imgur/models/custom_gallery.py
imgurpython/imgur/models/gallery_album.py
imgurpython/imgur/models/gallery_image.py
imgurpython/imgur/models/image.py
imgurpython/imgur/models/message.py
imgurpython/imgur/models/notification.py
imgurpython/imgur/models/tag.py
imgurpython/imgur/models/tag_vote.py
