Metadata-Version: 2.0
Name: imgurapi
Version: 1.1.9.1
Summary: Fork of the Official Imgur python library with OAuth2 and samples
Home-page: https://github.com/linuxdaemon/imgurpython
Author: linuxdaemon
Author-email: linuxdaemon.irc+pypi@gmail.com
License: MIT
Keywords: api,imgur,client
Platform: UNKNOWN
Classifier: Development Status :: 4 - Beta
Classifier: Intended Audience :: Developers
Classifier: License :: OSI Approved :: MIT License
Classifier: Programming Language :: Python :: 2.7
Classifier: Programming Language :: Python :: 3
Classifier: Programming Language :: Python :: 3.2
Classifier: Programming Language :: Python :: 3.3
Classifier: Programming Language :: Python :: 3.4
Requires-Dist: requests
